setup.cfg
setup.py
jhpythondev/__init__.py
jhpythondev/add.py
jhpythondev/division.py
jhpythondev/multiply.py
jhpythondev/subtract.py
jhpythondev.egg-info/PKG-INFO
jhpythondev.egg-info/SOURCES.txt
jhpythondev.egg-info/dependency_links.txt
jhpythondev.egg-info/top_level.txt
jhpythondev/adv/__init__.py
jhpythondev/adv/sqrt.py