Metadata-Version: 1.0
Name: jhpythondev
Version: 0.1
Summary: jhzq python package
Home-page: http://www.jhzq.com.cn/
Author: jhzq
Author-email: 70134917@qq.com
License: UNKNOWN
Platform: UNKNOWN
